{
    "m_Version": 6,
    "m_DisplayName": "Boat trader",
    "Position": [
        10511.400390625,
        1.9471060037612916,
        5723.33984375
    ],
    "Radius": 150.0,
    "BuyPricePercent": 100.0,
    "SellPricePercent": -1.0,
    "Stock": {
        "civsedandoors_driver_black": 0,
        "hatchback_02_trunk": 0,
        "sparkplug": 0,
        "expansionbuswheeldouble": 0,
        "civsedanhood": 0,
        "hatchback_02_door_1_2_blackrust": 75,
        "hatchbackhood_whiterust": 75,
        "expansionmerlinfrontwheel": 0,
        "expansion_mh6_door_2_2_black": 0,
        "hatchbackdoors_driver_white": 0,
        "hatchback_02_door_2_1_blue": 0,
        "expansion_landrover_left": 0,
        "hatchback_02_door_2_2_black": 0,
        "expansiontractorfrontwheel": 0,
        "sedan_02_door_2_1_grey": 0,
        "expansionigniterplug": 0,
        "hatchbackwheel": 0,
        "sedan_02_door_2_2_red": 0,
        "hatchbackdoors_driver_bluerust": 75,
        "expansion_landrover_right": 0,
        "expansionuazdoorcodriver": 0,
        "boat_01_orange": 7,
        "offroad_02_door_2_2_rust": 75,
        "offroad_02_door_2_1_rust": 75,
        "boat_01_blue": 7,
        "civsedantrunk_winerust": 75,
        "hatchbackdoors_codriver_bluerust": 75,
        "sedan_02_door_1_1": 0,
        "sedan_02_door_1_2": 0,
        "sedan_02_door_2_1_redrust": 75,
        "civsedandoors_codriver_black": 0,
        "truck_01_door_2_1_blue": 0,
        "sedan_02_door_1_2_yellowrust": 75,
        "hatchback_02_door_2_1_bluerust": 75,
        "civsedanwheel": 0,
        "sedan_02_hood_grey": 0,
        "sedan_02_door_2_1_greyrust": 75,
        "expansionkeychain_orange": 0,
        "offroad_02_door_1_1_rust": 75,
        "hatchbackdoors_driver": 0,
        "hatchback_02_trunk_blue": 0,
        "hatchback_02_trunk_blackrust": 75,
        "truck_01_wheeldouble": 0,
        "expansion_mh6_door_1_1_black": 0,
        "truck_01_door_1_1_greenrust": 75,
        "headlighth7": 0,
        "expansionuazdoordriver": 0,
        "hatchback_02_hood": 0,
        "hatchbacktrunk_whiterust": 75,
        "sedan_02_door_1_1_red": 0,
        "truck_01_door_2_1_bluerust": 75,
        "hatchback_02_door_1_1_black": 0,
        "hatchbackdoors_codriver_white": 0,
        "hatchback_02_door_1_1_redrust": 75,
        "carbattery": 0,
        "offroad_02_door_2_1": 0,
        "offroad_02_door_2_2": 0,
        "offroad_02_trunk_rust": 75,
        "truck_01_door_1_1_orange": 0,
        "expansion_landrover_trunk": 0,
        "hatchbackdoors_codriver": 0,
        "hatchback_02_trunk_redrust": 75,
        "civsedandoors_driver": 0,
        "hatchbackdoors_codriver_whiterust": 75,
        "civsedandoors_backleft_whiterust": 75,
        "hatchback_02_door_2_2_redrust": 75,
        "offroad_02_trunk": 0,
        "tirerepairkit": 0,
        "civsedandoors_backleft": 0,
        "hatchback_02_door_2_1_blackrust": 75,
        "sedan_02_trunk_grey": 0,
        "civsedandoors_backright_black": 0,
        "hatchback_02_hood_blackrust": 75,
        "sedan_02_hood_redrust": 75,
        "civsedandoors_codriver_wine": 0,
        "boat_01_black": 7,
        "hatchback_02_door_2_1_redrust": 75,
        "sedan_02_door_2_1_yellowrust": 75,
        "civsedandoors_backleft_blackrust": 75,
        "expansionkeychain_grey": 0,
        "hatchbacktrunk_blue": 0,
        "civsedanhood_whiterust": 75,
        "sedan_02_door_1_2_greyrust": 75,
        "civsedandoors_driver_whiterust": 75,
        "sedan_02_trunk_greyrust": 75,
        "civsedantrunk_wine": 0,
        "civsedandoors_backright_whiterust": 75,
        "expansionkeychain_pink": 0,
        "hatchback_02_hood_bluerust": 75,
        "truck_01_hood_greenrust": 75,
        "hatchback_02_door_1_1_blackrust": 75,
        "hatchback_02_wheel": 0,
        "hatchbackdoors_codriver_blue": 0,
        "hatchbacktrunk": 0,
        "expansiontractordoorsdriver": 0,
        "expansionlhd": 0,
        "battery9v": 0,
        "truck_01_door_2_1": 0,
        "sedan_02_hood_yellowrust": 75,
        "hatchback_02_door_2_2_blue": 0,
        "glowplug": 0,
        "expansiontractorbackwheel": 0,
        "sedan_02_door_2_2_greyrust": 75,
        "hatchback_02_door_2_2_bluerust": 75,
        "truck_01_wheel": 0,
        "hatchback_02_door_1_2_redrust": 75,
        "civsedantrunk": 0,
        "sedan_02_door_2_2_grey": 0,
        "sedan_02_wheel": 0,
        "hatchbacktrunk_white": 0,
        "truck_01_hood_orangerust": 75,
        "hatchback_02_trunk_black": 0,
        "expansionuazdoorhood": 0,
        "hatchback_02_door_1_1_blue": 0,
        "expansionzodiacboat": 0,
        "sedan_02_door_1_1_redrust": 75,
        "hatchbackhood_bluerust": 75,
        "truck_01_door_2_1_orange": 0,
        "civsedandoors_backleft_black": 0,
        "truck_01_door_1_1_bluerust": 75,
        "expansion_landrover_driverdoor": 0,
        "expansionvodnikwheel": 0,
        "sedan_02_door_2_2_redrust": 75,
        "offroad_02_hood": 0,
        "carradiator": 0,
        "offroad_02_door_1_1": 0,
        "offroad_02_door_1_2": 0,
        "offroad_02_door_1_2_rust": 75,
        "sedan_02_hood_greyrust": 75,
        "expansion_mh6_door_1_2_black": 0,
        "hatchback_02_door_1_1_bluerust": 75,
        "expansion_mh6_door_2_1": 0,
        "expansion_mh6_door_2_2": 0,
        "civsedandoors_driver_winerust": 75,
        "expansionuh1hdoor_2_1": 0,
        "expansionuh1hdoor_2_2": 0,
        "expansionvodnikdoorcodriver": 0,
        "hatchback_02_hood_redrust": 75,
        "civsedantrunk_whiterust": 75,
        "hatchback_02_door_1_2_black": 0,
        "expansionhydraulichoses": 0,
        "civsedandoors_codriver": 0,
        "civsedandoors_backright": 0,
        "expansion_mh6_door_2_1_black": 0,
        "truckbattery": 0,
        "hatchback_02_door_2_1": 0,
        "hatchback_02_door_2_2": 0,
        "expansionkeychain_purple": 75,
        "hatchbackhood_white": 0,
        "hatchbackhood_greenrust": 75,
        "hatchback_02_door_2_1_black": 0,
        "expansionuazdoorcargo2": 0,
        "civsedandoors_backright_winerust": 75,
        "sedan_02_trunk_red": 0,
        "sedan_02_door_1_1_grey": 0,
        "civsedandoors_driver_wine": 0,
        "expansion_landrover_hood": 0,
        "truck_01_hood_orange": 0,
        "sedan_02_door_1_2_red": 0,
        "hatchback_02_hood_black": 0,
        "expansiontractordoorscodriver": 0,
        "civsedandoors_codriver_whiterust": 75,
        "hatchbackdoors_driver_whiterust": 75,
        "truck_01_hood_bluerust": 75,
        "civsedanhood_wine": 0,
        "expansionmerlinbackwheel": 0,
        "expansionkeychain_white": 0,
        "expansionkeychain_yellow": 0,
        "civsedandoors_backright_wine": 0,
        "hatchbackhood_blue": 0,
        "sedan_02_trunk_redrust": 75,
        "expansionkeychain_green": 0,
        "civsedandoors_backleft_winerust": 75,
        "boat_01_camo": 7,
        "truck_01_door_2_1_greenrust": 75,
        "sedan_02_door_1_1_yellowrust": 75,
        "hatchback_02_trunk_bluerust": 75,
        "truck_01_door_1_1_orangerust": 75,
        "expansionkeychain_purp": 0,
        "expansionuazdoorcargo1": 0,
        "truck_01_hood_blue": 0,
        "civsedantrunk_blackrust": 75,
        "sedan_02_door_2_1": 0,
        "sedan_02_door_2_2": 0,
        "civsedanhood_winerust": 75,
        "hatchback_02_door_2_2_blackrust": 75,
        "sedan_02_hood": 0,
        "civsedandoors_codriver_blackrust": 75,
        "expansionbuswheel": 0,
        "civsedandoors_codriver_winerust": 75,
        "hatchbacktrunk_bluerust": 75,
        "sedan_02_trunk": 0,
        "sedan_02_door_1_1_greyrust": 75,
        "truck_01_door_1_1": 0,
        "hatchbackdoors_codriver_greenrust": 75,
        "hatchbackhood": 0,
        "civsedandoors_backleft_wine": 0,
        "civsedanhood_blackrust": 75,
        "expansionuazwheel": 0,
        "hatchback_02_door_1_2_bluerust": 75,
        "expansionkeychain_blue": 0,
        "civsedandoors_driver_blackrust": 75,
        "civsedanhood_black": 0,
        "civsedandoors_backright_blackrust": 75,
        "civsedantrunk_black": 0,
        "sedan_02_door_2_1_red": 0,
        "expansion_landrover_codriverdoor": 0,
        "truck_01_door_2_1_orangerust": 75,
        "truck_01_door_1_1_blue": 0,
        "offroad_02_wheel": 0,
        "expansionvodnikdoordriver": 0,
        "hatchbackdoors_driver_greenrust": 75,
        "expansion_mh6_door_1_1": 0,
        "expansion_mh6_door_1_2": 0,
        "sedan_02_door_2_2_yellowrust": 75,
        "hatchback_02_door_1_2_blue": 0,
        "hatchback_02_hood_blue": 0,
        "expansionuh1hdoor_1_1": 0,
        "expansionuh1hdoor_1_2": 0,
        "expansion_landrover_wheel": 0,
        "truck_01_hood": 0,
        "expansionutilityboat": 0,
        "hatchback_02_door_1_1": 0,
        "expansionkeychain_black": 0,
        "hatchbackdoors_driver_blue": 0,
        "hatchbacktrunk_greenrust": 75,
        "sedan_02_trunk_yellowrust": 75,
        "sedan_02_door_1_2_redrust": 75,
        "sedan_02_door_1_2_grey": 0,
        "sedan_02_hood_red": 0,
        "expansioncarkey": 0,
        "headlighth7_box": 0,
        "hatchback_02_door_1_2": 0,
        "expansionkeychain_red": 0,
        "expansionhelicopterbattery": 0
    }
}